{
    "LanguageCulture": "nb-NO",
    "clientLogo": "Kunde logo",
    "survey": "Unders\u00f8kelser",
    "profile": "Profil",
    "practiceArea": "Test omr\u00e5de",
    "settings": "Innstillinger",
    "help": "Hjelp",
    "signout": "Logg ut",
    "welcometxt":"Velkommen! Begynn \u00e5 gi oss dine tilbakemeldinger",
    "signintxt":"Logg inn for \u00e5 begynne. Om du ikke har dine innloggingsdetaljer enda",
    "clickhere":"Klikk her.",
    "usernamePH": "Brukernavn",
    "passwordPH": "Passord",
    "signin": "Logg inn",
    "emptymsg" : "Vennligst tast inn feltene",
    "wrongCredentials" : "Feil kombinasjon av brukernavn/passord",
    "termsofuse": "Brukervilk\u00e5r",
    "privacy": "Personvern",
    "faq":"Vanlige sp\u00f8rsm\u00e5l",
    "contact":"Kontakt oss",
    "About":"Om My Surveys Appen",
    "poweredBy":"Driftet",
    "welcome": "Hei",
    "panelMember":"du er medlem av flere paneler",
    "selectPanel": "Velg hvilket panel du vil logge inn til for \u00e5 svare p\u00e5 sp\u00f8rsm\u00e5l og tjene poeng. (du kan bytte over til et annet panel I innstillingene n\u00e5r som helst).",
    "selectPanelDefault": "Velg ditt panel",
    "selectPanelErr": "Vennligst velg et panel",
    "notification" : "Varslinger",
    "notificationlinktxt" : "Se alle varslinger",
    "pullToRefresh":"Dra ned for \u00e5 oppdatere",
    "estimatedTime": "Forventet tid",
    "occurance": "Deltakelse",
    "deadline": "Unders\u00f8kelsen er ferdig",
    "takeSurvey": "Ta unders\u00f8kelsen",
    "startSurvey" : "Start unders\u00f8kelsen",
    "surveyIncomplete": "Unders\u00f8kelser",
    "surveyComplete": "Fullf\u00f8rt",
    "surveyExisting": "Eksisterende",
    "surveyNew": "Ny",
    "surveys": "Unders\u00f8kelser",
    "noData": "Ingen unders\u00f8kelser p\u00e5 listen",
    "onlineStatus": "Online",
    "offlineStatus": "Offline",
    "correctErrors": "Rett opp feilene",
    "errFirstName": "Fornavn kan ikke st\u00e5 tomt",
    "errLastName": "Etternavn kan ikke st\u00e5 tomt",
    "errgender": "Vennligst velg kj\u00f8nn",
    "errmaritalStatus": "Vennligst velg status",
    "errDOB": "Vennligst velg f\u00f8dselsdato",
   "gender": "Kj\u00f8nn",
    "maritalStatus": "Status",
    "DOB": "F\u00f8dselsdato",
    "Email": "Epostadresse",
    "MobileNumber": "Mobilnummer",
    "edit":"edit",
    "delete":"delete",
    "editProfile": "Rediger profil",
    "cancel": "Avbryt",
    "uploadPhoto": "Last opp bilde",
    "editPhoto" : "Rediger bilde",
    "removePhoto": "Ta vekk bilde",
    "select" : "Velg",
    "chooseMedia": "Velg fra",
    "galleryOption": "Velg fra galleri",
    "cameraOption": "Ta bilde",
    "FirstNamePH": "Fornavn",
    "LastNamePH": "Etternavn",
    "DOBPH": "F\u00f8dselsdato",
    "genderPH": "Kj\u00f8nn",
    "maritalStatusPH": "Status",
    "genderPHOpt1": "Mann",
    "genderPHOpt2": "Kvinne",
    "maritalStatusPHOpt1": "Enslig",
    "maritalStatusPHOpt2": "Gift",
    "maritalStatusPHOpt3": "Skilt",
    "maritalStatusPHOpt4": "Enke/enkemann",
    "uploading":"Laster opp",
    "networkError": "Vennligst skru p\u00e5 nettverk",
    "geolocation_header": "Finn plassering",
    "barcode_header": "Scan barkode",
    "enterBarcode":"Vennligst tast inn barkode",
    "geolocation_text1": "For \u00e5 finne din plassering, vennligst trykk Neste. (En liste adresser kan lastes opp for \u00e5 starte unders\u00f8kelser basert p\u00e5 deltakerens plassering).",
    "geolocation_text2": "Din plassering er",
    "geolocation_text3" : "Trykk Oppdater for \u00e5 s\u00f8ke igjen",
    "barcode_text1": "Barkode Nei",
    "barcode_text2": "Ingen barkode valgt",
    "barcode_text3": "Scan barkode",
    "geoNetworkError": "Vennligst koble deg til ditt nettverk og klikk NESTE for \u00e5 laste p\u00e5 nytt",
    "permissionDenied": "Bruker f\u00e5r ikke tilgang til Geolocation",
	"positionUnavailable" : "Plassering ikke tilgjengelig n\u00e5",
     "timeout" : "Foresp\u00f8rsel om brukerplassering utgikk",
    "Password": "Passord",
    "Version": "Versjon",
    "Panel": "Panel",
    "changePassword": "Forandre passord",
    "oldpwdPH": "Gammelt passord",
    "newpwdPH": "Nytt passord",
    "confirmpwdPH": "Bekreft passord",
    "update": "Oppdatering",
    "changePwdError1": "Passord m\u00e5 fylles inn",
    "changePwdError2": "Passord m\u00e5 fylles inn",
    "changePwdError3": "Nytt og bekreftet passord m\u00e5 være like",
    "changePwdError4": "Gammelt passord er ikke riktig",
    "changePwdSuccess":"Passord forandret",
    "wrongPassword":"Dette passordet finnes ikke",
    "changePanelSuccess" : "Byttet panel",
    "changePanelError" : "En feil oppstod ved bytte av panel. Vennligst pr\u00f8v igjen.", 
    "FAQs": "Vanlige sp\u00f8rsm\u00e5l",
    "Support": "Hjelp",
    "close": "Lukk",
    "back": "Tilbake",
    "submit": "Send inn",
    "exitapp" : "Er du sikker p\u00e5 at du vil ut?",
    "signoutTxt" : "Er du sikker p\u00e5 at du vil logge ut?",
    "signoutErr" : "Kunne ikke logge deg inn. Vennligst pr\u00f8v igjen.",
    "genericError" : "Det oppstod en feil. Vennligst pr\u00f8v igjen eller kontakt oss.",
    "errorPage" : "Error Page",
    "noSessionDataErr" : "Sorry. The app cannot be started. Please logout and start again.",
    "correctErrors" : "Correct the errors",
    "errorPage": "Feilside",
    "positionUnavailable" : "Plassering er ikke tilgjengelig",
    "timeout" :"Foresp\u00f8rsel om brukerplassering utgikk",
    "alert": "Varsel",
    "ok" : "OK",
    "confirm" : "Bekreft",
    "hours" : "timer",
    "minutes" : "minutter",
    "seconds" : "sekunder",
    "times" : "tider",
    "next" : "Neste",
    "refresh":"Last p\u00e5 nytt",
    "noImage":"Ikke noe bilde funnet",
    "continue":"G\u00e5 videre",
    "pleaseWait":"Vennligst vent. Appen laster",
     "version": "Versjon 1.3.8",
    "practicearea":"Testomr\u00e5det er laget for deg. Her kan du leke deg med noen av funksjonene du finner i unders\u00f8kelser. Du kan bli kjent med plassering, pr\u00f8ve barkodeskanneren og pr\u00f8vekj\u00f8re en unders\u00f8kelse.",
    "MySurveysAppversion":"My Surveys App versjon",
    "Releasetorefresh":"Slipp for \u00e5 laste p\u00e5 nytt...",
    "WelcometotheMySurveys":"Velkommen til My Surveys Appen, en instinktiv, sofistikert og morsom app for \u00e5 ta del i mobilunders\u00f8kelser. For \u00e5 s\u00f8rge for at du mottar dine invitasjoner og bel\u00f8nninger, alltid ha den siste versjonen installert. Sjekk ved \u00e5 trykke oppdater.",
    "Loading...":"Laster",
    "Failed : Current Password does not exist":"Dette passordet finnes ikke",
    "Jan":"Januar",
    "Feb":"February",
    "Mar":"Mars",
    "Apr":"April",
    "May":"Mai",
    "Jun":"Juni",
    "Jul":"Juli",
    "Aug":"August",
    "Sep":"September",
    "Oct":"Oktober",
    "Nov":"November",
    "Dec":"Desember",
    "refreshNotify":"Dra ned for \u00e5 oppdatere",
    "update":"Oppdatering",
    "updateDesc":"App oppdatering tilgjengelig",
    "Upload_survey_results":"Last opp resultat av unders\u00f8kelser.",
    "upload_now":"Last opp",
    "Surveys_Uploaded_Successfully":"Unders\u00f8kelsene ble lastet opp",
    "All_Surveys_Uploaded_Successfully":"Alle unders\u00f8kelsene ble lastet opp",
    "upload_all":"Last opp alle",
    "Select_Any_one_Survey_To_Upload":"Velg hvilken unders\u00f8kelse du vil laste opp",
    "done":"Done"
}
